datacenter_common/core/logger.py
datacenter_common/schemas/__init__.py
datacenter_common/schemas/a_stock.py
datacenter_common/schemas/base.py
datacenter_common/schemas/hk_company_profile.py
datacenter_common/schemas/hk_stock.py
datacenter_common/schemas/hs_industry.py
datacenter_common/schemas/hs_industry_company.py
datacenter_common/schemas/index_basic.py
datacenter_common/schemas/index_company.py
datacenter_common/schemas/margin_account.py
datacenter_common/schemas/margin_analysis.py
datacenter_common/schemas/margin_detail.py
datacenter_common/schemas/results.py
datacenter_common/schemas/sw_industry.py
datacenter_common/schemas/sw_industry_company.py
datacenter_common/utils/auth_token.py
datacenter_common/utils/baidu_utils.py
datacenter_common/utils/cache_utils.py
datacenter_common/utils/config_reader.py
datacenter_common/utils/eastmoney_utils.py
datacenter_common/utils/jin10_utils.py
datacenter_common/utils/logging_config.py
datacenter_common/utils/markdown_convert.py
datacenter_common/utils/money_format.py
datacenter_common/utils/proxy_utils.py
datacenter_common/utils/schema_extract.py
datacenter_common/utils/xueqiu_utils.py
alphaaidig_datacenter_common-0.1.23.dist-info/METADATA
alphaaidig_datacenter_common-0.1.23.dist-info/WHEEL
alphaaidig_datacenter_common-0.1.23.dist-info/top_level.txt
alphaaidig_datacenter_common-0.1.23.dist-info/RECORD
